zoid/Daemon.py
zoid/IS.py
zoid/Server.py
zoid/SourceRcon.py
zoid/Steam.py
zoid/Util.py
zoid/__init__.py
zoid/bytesize.py
zoid/API/__init__.py
zoid-0.2.3.data/scripts/zoid-backup
zoid-0.2.3.data/scripts/zoid-create
zoid-0.2.3.data/scripts/zoid-daemon
zoid-0.2.3.data/scripts/zoid-init
zoid-0.2.3.data/scripts/zoid-kill
zoid-0.2.3.data/scripts/zoid-ls
zoid-0.2.3.data/scripts/zoid-restart
zoid-0.2.3.data/scripts/zoid-start
zoid-0.2.3.data/scripts/zoid-stop
zoid-0.2.3.data/scripts/zoid-validate
zoid-0.2.3.dist-info/DESCRIPTION.rst
zoid-0.2.3.dist-info/METADATA
zoid-0.2.3.dist-info/RECORD
zoid-0.2.3.dist-info/WHEEL
zoid-0.2.3.dist-info/dependency_links.txt
zoid-0.2.3.dist-info/metadata.json
zoid-0.2.3.dist-info/top_level.txt
