Metadata-Version: 2.0
Name: zoid
Version: 0.2.3
Summary: Commandline tool for easy hosting of project zomboid servers
Home-page: https://bitbucket.org/uranoxyd/zoid/
Author: David Ewelt
Author-email: uranoxyd@gmail.com
License: BSD
Platform: UNKNOWN
Classifier: Development Status :: 3 - Alpha
Classifier: Intended Audience :: End Users/Desktop
Classifier: Topic :: Games/Entertainment
Classifier: Programming Language :: Python :: 2
Classifier: Programming Language :: Python :: 2.6
Classifier: Programming Language :: Python :: 2.7
Requires-Dist: uconfig (>=0.1.1)
